chainreader/__init__.py
chainreader/cache_manager.py
chainreader/chain_client.py
chainreader/chainreader.py
chainreader/exceptions.py
chainreader/provider_manager.py
chainreader/request_handler.py
chainreader-0.1.0.dist-info/licenses/LICENSE
chainreader-0.1.0.dist-info/METADATA
chainreader-0.1.0.dist-info/WHEEL
chainreader-0.1.0.dist-info/top_level.txt
chainreader-0.1.0.dist-info/RECORD
