Metadata-Version: 2.4
Name: chainreader
Version: 0.1.0
Summary: EVM-compatible blockchain data reader with intelligent RPC provider management, automatic failover, and smart caching
Author: ChainReader Contributors
License: MIT
Project-URL: Homepage, https://github.com/TickTockBent/chainreader
Project-URL: Documentation, https://github.com/TickTockBent/chainreader#readme
Project-URL: Repository, https://github.com/TickTockBent/chainreader
Project-URL: Issues, https://github.com/TickTockBent/chainreader/issues
Keywords: blockchain,ethereum,web3,rpc,evm,polygon,bsc,arbitrum
Classifier: Development Status :: 3 - Alpha
Classifier: Intended Audience :: Developers
Classifier: License :: OSI Approved :: MIT License
Classifier: Programming Language :: Python :: 3
Classifier: Programming Language :: Python :: 3.9
Classifier: Programming Language :: Python :: 3.10
Classifier: Programming Language :: Python :: 3.11
Classifier: Programming Language :: Python :: 3.12
Classifier: Topic :: Software Development :: Libraries :: Python Modules
Classifier: Topic :: System :: Distributed Computing
Requires-Python: >=3.9
License-File: LICENSE
Requires-Dist: web3>=6.0.0
Requires-Dist: aiohttp>=3.9.0
Requires-Dist: pydantic>=2.0.0
Requires-Dist: tenacity>=8.0.0
Provides-Extra: dev
Requires-Dist: pytest>=7.0.0; extra == "dev"
Requires-Dist: pytest-asyncio>=0.21.0; extra == "dev"
Requires-Dist: pytest-cov>=4.0.0; extra == "dev"
Requires-Dist: black>=23.0.0; extra == "dev"
Requires-Dist: mypy>=1.0.0; extra == "dev"
Requires-Dist: ruff>=0.1.0; extra == "dev"
Requires-Dist: pre-commit>=3.0.0; extra == "dev"
Dynamic: license-file
